{"all": ["the", "they", "acting", "laughter", "my", "the", "the", "my", "of", "of", "my", "my", "my"], "gt": ["in"], "forget": ["all"], "dance": [" "], "skip": ["the"], "beware": ["of", "of"], "people": ["smart"], "monte": ["carlo"], "yellow": [" "], "steve": ["like"], "groceries": ["please"], "hanging": ["slanging"], "go": ["again", "hard", "hard", "hard", "hard", "hard", "to"], "follow": ["your"], "everyones": ["around", "around"], "children": ["then"], "carpet": [" "], " ": ["hello", "i", "i", "think", "countin\u2019", "trap", "i", "i", "think", "countin\u2019", "trap", "button", "i", "it", "man", "someone", "everything", "phone", "phone", "call", "keep", "kitchen", "i", "i", "i", "think", "countin\u2019", "trap", "i", "i", "think", "countin\u2019", "trap", "there", "they", "all", "how", "what", "brick", "section", "rappin", "jumpin", "askin", "one", "everything", "partners", "juggin", "bread", "i", "i", "think", "countin\u2019", "trap", "i", "i", "think", "countin\u2019", "trap", "getting", "when", "money", "you", "weight", "smell", "conversation", "she", "engagin", "and", "amazing", "maybe", "maybe", "phone", "i", "i", "think", "countin\u2019", "trap", "i", "i", "think", "countin\u2019", "trap", "i", "i", "i", "get", "and", "i", "and", "i", "and", "i", "get", "full", "asked", "learn", "if", "iron", "on", "rap", "kill", "first", "kevin", "made", "dive", "got", "aim", "at", "only", "i", "i", "i", "get", "and", "i", "and", "i", "and", "i", "get", "me", "we", "couldnt", "steal", "our", "the", "keeping", "they", "six", "most", "right", "balenciaga", "chick", "and", "look", "pray", "i", "i", "i", "get", "and", "i", "and", "i", "and", "i", "get", "only", "dont", "dont", "aint", "only", "dont", "dont", "get", "only", "dont", "dont", "aint", "only", "dont", "dont", "get", "i", "i", "i", "get", "and", "i", "and", "i", "and", "i", "get", "and", "and", "and", "get", "and", "they", "my", "all", "bad", "they", "got", "i", "i", "they", "im", "make", "a", "bringing", "i", "achoo", "she", "actually", "not", "gates", "all", "scared", "he", "passing", "shout", "grey", "just", "my", "pockets", "steve", "working", "i", "body", "jhen\u00e9", "groceries", "all", "bad", "they", "got", "i", "i", "they", "im", "pray", "keep", "right", "when", "no", "where", "i", "take", "what", "what", "spreading", "pulling", "trying", "she", "oyster", "mustang", "trunk", "i", "shopping", "loving", "carats", "feeling", "all", "bad", "they", "got", "i", "i", "they", "im", "say", "or", "just", "evil", "keep", "of", "they", "they", "incident", "i", "and", "god", "i", "showing", "do", "took", "then", "when", "killing", "when", "killing", "they", "you", "changing", "pretending", "these", "i", "it", "she", "this", "hard", "memories", "she", "i", "reason", "every", "after", "its", "and", "when", "killing", "when", "killing", "they", "you", "changing", "pretending", "dont", "not", "im", "im", "im", "skip", "bandz", "with", "got", "acting", "put", "duffel", "she", "she", "my", "the", "long", "sayin", "i", "knock", "me", "imma", "im", "if", "and", "wait", "head", "bet", "man", "stupid", "like", "first"], "swag": ["women"], "ware": ["on"], "imma": ["put", "get", "put"], "balenciaga": ["be"], "father": ["full"], "acting": [" ", "bad"], "achoo": ["that"], "to": ["see", "bother", "give", "lend", "the", "get", "pull", "get", "pull", "what", "say", "the", "god", "god", "get", "pull", "get", "pull", "get", "sneeze", "you", "kevin", "switch", "holler", "black", "cedric", "god", "read", "pleasure", "pressin", "see", "drive", "the", "hold", "sleep", "sleep", "the"], "chewing": ["her"], "suite": [" "], "sorry": [" ", " ", " ", " "], "gravel": [" "], "necklaces": [" "], "me": ["while", "she", "baby", "and", "and", "if", "if", "if", "back", " ", "if", "if", "a", "if", "if", "put", "help", "forget", "seem", " ", "jumping", "straight", " ", " ", " ", "and"], "woman": ["i", "to"], "returned": ["the"], "song": ["writer", "and"], "none": ["of"], "pressin": ["her"], "every": ["time", "ones", "bitch", "ones"], "cellular": [" ", " "], "bringing": ["in"], "four": ["times"], "pallbearer": [" "], "did": ["i", "and"], "button": ["start"], "bright": ["\u2018cause"], "these": ["murders"], "sand": ["and"], "swallow": ["nut", "all"], "small": ["matter"], "sleep": ["on", " ", " "], "gardere": ["to"], "round": ["the", "me"], "cetera": [" "], "work": ["i"], "booty": ["on"], "tired": [" ", " ", " ", " ", " ", " ", " ", " ", "i", " ", " ", " ", " ", " ", " ", " ", " ", " ", " ", " ", " ", " ", " ", " ", " ", "i", "i", " ", "i", "i", " ", " ", " ", " ", " ", " ", " ", " ", " ", " ", " ", " ", " "], "phones": ["one", "one", "one", "one", "one", "one", "one", "one", "one", "one", "one", "one", "one", "one", "one", "one"], "streets": ["smoking", " "], "likely": ["the"], "steppin": [" "], "booth": ["no"], "infiltration": [" "], "carlo": ["cocaine"], "fear": ["no"], "shining": ["bright"], "even": ["when", "speak", "knew"], "what": ["the", "i", "i", "i", "i", "i", "you", "it", "it", "they", "can", "you", "you"], "betraying": ["beware", "beware"], "barbie": ["doll"], "section": ["doin", "ridiculous"], "thiiiiick": [" "], "above": ["we", "placing"], "new": ["ferrari", "performance"], "ever": ["fail", " "], "told": ["him", "me"], "body": ["unique", " ", "i"], "full": ["time", "time", "of", "of"], "submitted": ["by"], "men": ["believe"], "here": [" ", "i", "for", "vip"], "water": [" "], "let": ["in"], "trunk": ["in"], "sing": [" "], "strong": ["in"], "change": ["been", "been"], "wait": ["til"], "kids": [" "], "daughter": ["gon"], "didnt": ["do", "believe"], "leaves": [" "], "thats": ["irregular"], "dick": [" ", " ", " ", " ", "probably"], "love": ["on", "this", "you", "you", "you"], "win": ["no"], "feelings": ["she"], "bro": ["i"], "ask": ["me", "me", "me", "me", "me", "me", "me"], "vip": [" "], "raking": ["in"], "glance": [" "], "cocaine": ["911"], "everybody": ["in"], "from": ["your", "every", "the", "the", "the", "above"], "working": ["in"], "wiped": ["off"], "hungry": ["pack"], "texting": ["my"], "two": ["phones", "phones", "more", "phones", "phones", "more", "phones", "phones", "more", "phones", "phones", "more", "phones", "phones", "more", "phones", "phones", "more", "phones", "phones", "more", "phones", "phones", "more"], "live": [" ", " ", " ", " "], "call": ["my", "after", "me"], "gorgeous": [" "], "thru": ["gardere"], "tell": ["them", "by"], "more": ["line", "line", "line", "line", "line", "line", "line", "line"], "tryna": ["get"], "popped": ["and"], "sharing": ["that"], "babe": ["its"], "on": ["the", "sale", "the", "they", "it", "an", "the", "my", "indigent", "fleek", "my", "no", "my", "top", "my", "the", "constant", "my", "them", "her"], "afford": ["flights", " "], "hurt": ["you"], "phone": ["be", "be", "ringing", "disconnectin", "talking"], "chancethey": ["gon"], "baby": ["girl"], "hold": ["up", "me"], "women": ["feel", "tailor"], "shoot": ["for"], "keeping": ["the"], "word": ["from"], "this": ["a", " ", "from", "from", "bitch", "you", "message", "moscato", "broccoli", "three", "bitch"], "car": ["my"], "ride": ["like"], "getting": ["calling"], "soul": ["people"], "can": ["make", "happen", "sing", "tell"], "drill": ["i"], "learn": ["what", "from"], "making": ["women", "no"], "laughter": [" "], "heart": [" ", "in"], "recordin": [" "], "tap": ["first"], "want": ["them", "to", "them", "to", "them", "to", "them", "to", "her"], "give": ["a", " ", "up", "her"], "disconnectin": ["her"], "share": ["a"], "high": ["i", "i", "i"], "callin": ["i", "for"], "pulling": ["her"], "numbers": ["nowhere"], "purchased": ["a"], "sharp": ["observation"], "counting": ["your"], "ones": ["around", "around"], "awkward": ["that", "that"], "conversation": ["cause"], "travel": [" "], "six": ["jobs", "jobs", "jobs", "jobs", "weeks", "jobs", "jobs", "jobs", "jobs", "jobs", "jobs", "jobs"], "how": ["you", "a", "much", "i", "i", "i", "i"], "amazing": ["clip"], "elephant": [" ", " "], "pleasure": ["her"], "okay": ["to"], "mess": ["with", "with", "with"], "stop": ["popped"], "dive": ["in"], "after": [" ", "your", "three"], "ball": [" ", " ", " ", " "], "questioning": [" "], "bumpin\u2019": ["i\u2019m", "i\u2019m", "i\u2019m", "i\u2019m", "i\u2019m", "i\u2019m", "i\u2019m", "i\u2019m"], "wrong": ["if"], "lot": ["of", "of"], "wrist": [" "], "countin\u2019": ["money", "money", "money", "money", "money", "money", "money", "money"], "lesbian": [" "], "man": ["in", "thats", " ", "that"], "a": ["new", "damn", "nigga", "gym", "honda", "lot", "lot", "pallbearer", "call", "air", "cot", "foreign", "glance", "lyrical", "blessing", "bet", "replica", "elephant", "song", "body", "hungry", "man", "ball", "ball", "woman", "major", "fucked", "ball", "ball", "make", "bag", "model", "dog", "lesbian", "dentist", "drill"], "conscious": ["as"], "maybe": ["we", "i"], "switch": ["up"], "tailor": ["keep"], "jail": ["gotta"], "tall": ["and"], "thinkin": ["too"], "help": ["me"], "over": ["here"], "paper": ["to"], "dough": [" ", " ", " ", " ", " ", " ", " ", " "], "smiling": ["faces", "faces", "faces", "faces"], "its": ["all", "okay", "this", "not", "ok", "a"], "astrology": [" "], "somewhere": ["on"], "mattress": [" "], "choose": ["to"], "weeks": ["ago", "of"], "might": ["not", "say"], "into": ["astrology"], "then": ["he", "came", "put", "i"], "them": [" ", "dead", "dead", "get", "dead", "dead", "tabs", "bitches"], "someone": ["said"], "crash": [" "], "yo": ["bitch", "bitch"], "smarter": [" "], "bothering": ["me"], "they": ["ring", "ring", "callin", "unimportant", "ring", "ring", "go", "dont", "wanna", "ring", "ring", "ring", "ring", "hindquarters", "all", "didnt", "say", "ask", "really", "be", "ask", "ask", "yellow", "really", "be", "ask", "ask", "glisten", "really", "be", "ask", "ask", "get", "be", "comments", "teeth", "say", "love", "do", "fucking", "say", "love", "do", "mouth", "swallow"], "hands": [" "], "foot": ["on"], "day": ["you"], "bread": ["winner"], "wont": ["apologize", "apologize", "apologize", "even"], "geranimo": [" "], "times": ["my"], "trav": ["im"], "trap": ["jumpin", "jumpin", "jumpin", "jumpin", "jumpin", "jumpin", "jumpin", "jumpin"], "side": ["yelling", "of"], "em": ["believe", "believe", "tall", "black"], "attachments": ["with", "with", "with", "with"], "weight": ["shape"], "doing": ["the", "her"], "hard": [" ", " ", " ", " ", " ", "to"], "oil": ["cause"], "our": ["testament"], "girl": ["im", "and", "swallow"], "message": [" "], "special": ["to", " "], "out": ["a", "of", "my", "to", "to", "my", "my", "my", "texting", "my", "i", "that", " "], "gon": ["love", "hit", "hurt", "make"], "alcohol": [" ", " ", " ", " "], "god": ["im", "he", "we", "we", "that", "protected"], "ringin\u2019": [" ", " ", " ", " ", " ", " ", " ", " ", " ", " ", " ", " ", " ", " ", " ", " ", " ", " ", " ", " ", " ", " ", " ", " "], "looking": ["in"], "reverend": [" "], "krispies": ["like"], "safety": ["harness", "on"], "got": ["two", "two", "two", "two", "it", "two", "two", "two", "two", "to", "to", "it", "two", "two", "two", "two", "two", "two", "two", "two", "six", "six", "in", "six", "six", "six", "six", "six", "six", "six", "six", "six", "money", "money", "money", "the", "my", "the"], "cause": ["i", "a"], "deceptions": [" "], "glover": [" "], "ass": ["in", "nigga"], "inhaling": ["sticks"], "reason": ["i"], "put": ["the", "that", "you", "syrup", "him", "me", "that", "her"], "wanted": ["to"], "care": ["of"], "advance": [" "], "steal": ["rice"], "messages": [" "], "keep": ["the", "it", "checking", "the"], "thing": ["dont", "dont", "dont", "dont", "dont", " ", " "], "jumping": ["up"], "testament": ["to"], "think": ["i", "i", "i", "i", "i", "i", "i", "i"], "first": ["look", "then", "made", "they"], "feed": ["the"], "major": ["psychology"], "placing": ["my"], "dont": ["feel", "give", "really", "get", "get", "get", "get", "get", "get", "get", "get", "get", "get", "get", "get", "get", "get", "get", "get", "get", "get", "get", "get", "get", "get", "get", "pray", "crash", "get", "get", "get", "get", "get", "get", "get", "get", "get", "get", "get", "get", "play", "mimic", "get", "play", "mimic", "get", "get", "play", "mimic", "get", "play", "mimic", "get", "get", "get", "get", "get", "get", "get", "get", "get", "get", "get", "get", "get", "get", "get", "get", "look", "call", "nobody", "mess", "mess", "be", "speak", "say", "say", "want", "clap"], "feel": ["like", "they", "david"], "one": ["for", "for", "for", "for", "for", "for", "for", "for", "for", "for", "for", "for", "for", "for", "for", "for", "of", "day", "for", "for", "for", "for", "for", "for", "for", "for", "for", "for", "for", "for", "for", "for", "for", "for", "thing", "that", "thing", "thing", "thing", "thing"], "fucked": ["up"], "bitch": ["here", "over", "you", "im", "wiped", "aint", "again", " ", " ", "was"], "comin": ["in"], "says": ["a"], "ring": ["ring", "ringin\u2019", "ring", "ringin\u2019", "ring", "ringin\u2019", "ring", "ringin\u2019", "ring", "ringin\u2019", "ring", "ringin\u2019", "ring", "ringin\u2019", "ring", "ringin\u2019", "ring", "ringin\u2019", "ring", "ringin\u2019", "ring", "ringin\u2019", "ring", "ringin\u2019", "ring", "ringin\u2019", "ring", "ringin\u2019", "ring", "ringin\u2019", "ring", "ringin\u2019", "ring", "ringin\u2019", "ring", "ringin\u2019", "ring", "ringin\u2019", "ring", "ringin\u2019", "ring", "ringin\u2019", "ring", "ringin\u2019", "ring", "ringin\u2019", "ring", "ringin\u2019"], "ballin": ["\u2018cause", " ", "\u2018cause", " ", "\u2018cause", " "], "city": ["you"], "glisten": ["in"], "top": ["of"], "anyone": ["testing"], "their": ["eyes", "eyes"], "too": ["impatient", "careful", "many", "much", "pretty"], "white": ["teeth"], "legs": ["bout"], "syrup": ["in", "my"], "undressin": ["her"], "way": ["i", "retarded"], "that": ["on", "important", "you", "im", "she", "was", "was", "dont", "for", "for", "for", "their", "for", "their", "ass", "bitch", "bitch", "we", "bitch", "girl"], "gym": [" "], "nobody": ["makin", "mess"], "park": [" "], "shorty": ["be"], "trippy": ["with"], "dentist": ["with"], "ridiculous": ["watch"], "loving": ["my"], "believe": ["what", " ", "i", " "], "toronto": ["she"], "10": [" "], "bodyguard": [" "], "anxiety": ["be"], "rappin": ["bottles"], "bother": [" "], "grey": ["monte"], "flashed": ["out"], "matter": [" "], "protected": ["my"], "iron": ["sharpens"], "cards": ["from"], "feeling": ["myself", "when"], "bet": [" ", "with", "you", "you", "you", "you", "you"], "and": ["one", "one", "one", "one", "one", "one", "one", "one", "what", "one", "one", "one", "one", "aint", "one", "one", "one", "one", "i", "i", "i", "they", "get", "i", "i", "i", "i", "the", "gravel", "its", "i", "i", "i", "i", "i", "i", "i", "i", "i", "i", "im", "he", "when", "told", "he", "goliath", "that", "everybody", "that", "squat", "this", "why", "her"], "liqour": [" "], "flights": ["no"], "clip": ["hanging"], "tabs": [" "], "mind": ["i", "i", "i", "i", "i", "i", " "], "eyes": ["dont", "dont"], "dash": [" "], "talking": ["reckless", "violent"], "say": ["its", "give", "that", "is", "really", "really", "really", "really", "really", "really", "really", "really", "we", "really", "really", "really", "really", "bro", "they", "the", "babe", "they", "the"], "rap": ["game"], "spectacle": [" "], "need": ["two", "two", "two", "two", "two", "two", "two", "two", "that", "that", "a"], "my": ["god", "pocket", "dog", "lil", "hair", "daughter", "diamonds", "mind", "mind", "cellular", "section", "diamonds", "mind", "mind", "beverages", "etiquette", "swag", "necklaces", "diamonds", "mind", "mind", "heart", "car", "nigga", "phone", "body", "lick", "conscious", "problems", "sleep", "life", "anxiety", "dick", "dick", "dick", "mind", "vans", "hands", "dick", "children"], "seem": ["too"], "saw": ["that"], "kevin": ["gates", " "], "squat": ["by"], "lil": ["friends"], "click": ["down"], "take": ["her", "too"], "performance": [" "], "foreman": [" "], "play": ["with", "with", "with", "with"], "mileage": [" "], "juggin": ["round"], "who": ["you", "you", "you", "you", "tap"], "took": ["my"], "most": ["likely"], "regular": [" "], "mouth": [" "], "jumpin": ["i\u2019m", "i\u2019m", "i\u2019m", "i\u2019m", "out", "i\u2019m", "i\u2019m", "i\u2019m", "i\u2019m"], "jhen\u00e9": ["aiko"], "model": ["imma"], "oyster": ["perpetual"], "observation": ["allowing"], "sale": ["goin"], "face": ["but"], "psychology": ["would"], "ferrari": [" "], "hips": [" "], "detective": ["work"], "walking": [" "], "lyrics": ["submitted"], "etiquette": [" "], "please": ["you"], "lay": ["on"], "attempts": [" "], "gazin": ["at"], "takin": ["trips"], "find": ["it", "out", "it", "out"], "aint": ["nobody", "win", "never", "never", "shit", "talkin", "gon"], "partners": ["up"], "sayin": ["i"], "front": ["do"], "winner": ["business"], "only": ["meaning", "meaning", "meaning", "meaning", "meaning"], "black": ["shout", "pretty"], "pretty": ["white", "in"], "circle": [" "], "rice": ["krispies"], "do": ["for", "all", "it", "it", "anything", "this", "anything"], "hit": ["it"], "get": ["to", " ", "a", "it", "it", "fly", "tired", "tired", "i", "tired", "tired", "i", "tired", "tired", "i", "tired", "it", "fly", "tired", "a", "tired", "it", "it", "fly", "tired", "tired", "i", "tired", "tired", "i", "tired", "tired", "i", "tired", "it", "fly", "tired", "dark", "lost", "it", "it", "fly", "tired", "tired", "i", "tired", "tired", "i", "tired", "tired", "i", "tired", "it", "fly", "tired", "tired", "tired", "it", "fly", "tired", "tired", "tired", "it", "fly", "tired", "it", "it", "fly", "tired", "tired", "i", "tired", "tired", "i", "tired", "tired", "i", "tired", "it", "fly", "tired", "tired", "tired", "tired", "it", "fly", "tired", "paper", "the", "her"], "honda": ["i"], "watch": ["where"], "pocket": ["park"], "unimportant": [" "], "cannot": ["afford"], "pretending": ["betraying", "they", "betraying"], "chips": [" "], "him": [" ", "no", "in"], "artist": [" "], "violent": [" "], "calling": ["cards"], "bag": ["full", "full"], "bad": [" ", "bitches", "bitches", "bitches", "on"], "stupid": ["nigga"], "she": ["round", "know", "dont", "bad", "special", "been", "catching", "say", "down", "says", "might", "walking", "super", "a", "stop", "was"], "where": ["im", "you", "she"], "gotta": ["feed"], "nut": ["like"], "testing": ["us"], "sharpens": ["you"], "see": ["this", "who"], "college": ["fresh", " "], "are": [" ", " ", " ", " "], "fail": [" ", "just"], "concern": [" "], "knees": ["right"], "said": ["they", "grind"], "grindin": [" "], "diamonds": ["shine", " ", "shine", " ", "shine", " "], "probably": ["trynna", "wont", "thought"], "bought": ["it"], "we": ["can", "share", "dont", "dont", "not", "do", "inseparable", "sharing"], "interrupting": ["me"], "jobs": ["i", "i", "i", "i", "i", "i", "i", "i", "i", "i", "i"], "trynna": ["kill"], "breathin": [" "], "marvin": ["strawder"], "beverages": [" "], "inseparable": [" "], "killing": ["emotional", "emotional", "emotional", "emotional"], "incident": ["with"], "awards": ["i", " "], "key": ["inside"], "cedric": [" "], "zipper": [" "], "lyrical": ["song"], "kitchen": ["i"], "cop": ["none"], "cot": ["my"], "irregular": [" "], "many": ["showers"], "taking": ["care"], "foreign": ["oh", " "], "pray": ["to", "to", "to"], "retarded": [" "], "passing": ["thru"], "whole": ["click"], "asked": ["god"], "load": [" ", " ", " ", " ", " ", " ", " ", " "], "sweet": ["inhaling"], "makin": ["no"], "lick": ["like"], "supplin": ["10"], "actually": ["i"], "speak": ["on", " "], "quit": ["syrup"], "three": ["of", "weeks"], "been": [" ", "like", "like", "ballin", "ballin", "trying", "ballin"], "much": ["did", "is"], "damn": ["how"], "treat": ["her"], "latelybeware": ["of", "of"], "brick": ["comin"], "shine": ["\u2018cause", "\u2018cause", "\u2018cause"], "life": ["on"], "shopping": ["in"], "both": ["into"], "blessing": [" "], "gas": [" ", " "], "finished": ["up"], "hindquarters": ["and"], "smoking": ["vegetables"], "careful": [" "], "spin": ["im"], "bout": ["to", "conical"], "those": ["you"], "case": ["anyone"], "myself": ["really"], "look": ["it", "to", "like", "at", "like", "like", "like"], "fleek": [" "], "checking": ["it"], "straight": ["back"], "harder": [" "], "cash": [" "], "air": ["mattress", "travel"], "aim": ["and"], "while": ["they", "they", "im", "they", "they", "they", "they", "they", "they"], "kick": ["them"], "murders": ["ware"], "pack": ["of"], "bandz": ["a"], "would": ["both"], "ringing": ["hold"], "is": ["different", "what", " ", " ", "you", "after", "bothering"], "it": ["might", " ", "off", "in", "is", "takin", "is", "how", "get", "get", "never", "was", " ", "how", "get", "get", "get", "how", "get", "get", "get", "get", "how", "get", "get", "get", "strong", " ", "make", " ", "was", " ", " ", " ", "look", "awkward", "5", "awkward", "dont", "to"], "cant": ["be", "quit"], "rim": [" "], "im": ["gorgeous", "recordin", "supplin", "her", "sorry", "gazin", "a", "doing", "with", "shining", "really", "real", "high", "really", "not", "lying", "really", "like", "high", "really", "not", "lying", "really", "high", "really", "not", "lying", "really", "eating", "cheesing", "with", "just", "just", "just", "a", "not"], "in": ["the", "somewhere", " ", "jail", "the", "the", "the", "line", "money", "leaves", "college", "line", "case", "the", "the", "my", "beverly", "all", "line", "this", "your", "a", "toronto", "the", "the", "the", "advance", "my", "they"], "conical": [" "], "if": ["it", "im", "im", "im", "im", "im", "its", "im", "im", "it", "i"], "different": ["returned"], "bottles": ["spin"], "make": ["it", "em", "me", "her", "it"], "same": ["thing", "thing"], "check": ["out"], "writer": ["and"], "digging": ["in"], "shawty": ["ride"], "slanging": ["dick"], "askin": ["what"], "pretenders": ["just", "just", "just", "just"], "faces": [" ", " ", " ", "lyrics"], "evil": ["is"], "\u2018cause": ["im", "they", "im", "they", "im", "they", "im"], "moment": ["you"], "feds": ["had"], "never": ["fail", "change", "change", "even"], "haunting": ["me"], "changing": ["latelybeware", "latelybeware"], "broccoli": [" "], "off": ["the", "the"], "i": ["got", "got", "need", "got", "got", "need", "just", "dont", "bought", "am", "just", "just", "got", "got", "need", "got", "got", "need", "got", "spend", "got", "did", "didnt", "just", "cop", "got", "got", "need", "got", "got", "need", "was", "got", "got", "need", "got", "got", "need", "was", "live", "want", "want", "got", "dont", "dont", "dont", "dont", "dont", "dont", "dont", "dont", "dont", "dont", "got", "dont", "shoot", "aint", "go", "was", "live", "want", "want", "got", "dont", "dont", "dont", "dont", "dont", "dont", "dont", "dont", "dont", "dont", "got", "dont", "love", "tell", "just", "give", "was", "live", "want", "want", "got", "dont", "dont", "dont", "dont", "dont", "dont", "dont", "dont", "dont", "dont", "got", "dont", "go", "go", "got", "dont", "go", "go", "got", "dont", "was", "live", "want", "want", "got", "dont", "dont", "dont", "dont", "dont", "dont", "dont", "dont", "dont", "dont", "got", "dont", "dont", "dont", "dont", "got", "dont", "say", "say", "say", "look", "been", "wont", "say", "say", "made", "was", "dont", "treat", "like", "say", "say", "look", "been", "wont", "say", "say", "dont", "dont", "dont", "really", "say", "say", "look", "been", "wont", "say", "say", "love", "told", "fear", "feel", "bet", "bet", "take", "need", "do", "cant", "aint", "bet", "bet", "got", "aint", "saw", "probably", "be", "kick"], "spent": [" ", " ", " ", " "], "grind": ["harder", "smarter"], "thought": ["it", "yo"], "the": ["deal", "plug", "load", "bitches", "dough", "plug", "load", "bitches", "dough", "foreign", "key", "mirror", "way", "way", "oil", "foreman", "scale", "plug", "load", "bitches", "dough", "plug", "load", "bitches", "dough", "rim", "kids", "city", "wrist", "plug", "load", "bitches", "dough", "plug", "load", "bitches", "dough", "carpet", "water", "plug", "load", "bitches", "dough", "plug", "load", "bitches", "dough", "dagger", "crowd", "booth", "stars", "awards", "woman", "moment", "faith", "one", "gas", "dash", "right", "hustle", "start", "hustle", "hustle", "start", "hustle", "above", "et", "feds", "reverend", "back", "streets", "front", "word", "sharp", "chancethey", "streets", "alcohol", "alcohol", "same", "side", "mirror", "mirror", "alcohol", "alcohol", "same", "face", "line", "zipper", "bitch", "liqour", "gas", "whole", "suite"], "spend": ["what"], "nappy": [" "], "i\u2019m": ["ring", "ring", "ring", "ring", "ring", "ring", "ring", "ring", "ring", "ring", "ring", "ring", "ring", "ring", "ring", "ring"], "gates": ["no", "had"], "cheesing": [" "], "just": ["put", "finished", "got", "got", "side", "grind", "purchased", "be", "be", "be", "be", "trying", "hollered", "got", "fucking", "thinking", "thinking", "thinking"], "being": ["seen"], "money": ["while", "while", "while", "while", "while", "while", "callin", "while", "while", "on", "like", "on", "on"], "seen": ["we"], "not": ["get", "using", "that", "really", "being", "making", "really", "a", "really", "too", "fucking"], "shape": ["her"], "kill": ["me", "her"], "death": ["but"], "caressin": ["her"], "thinking": ["with", "with", "with"], "drive": ["it"], "had": ["her", "to", "a", "a", "a", "a"], "shout": ["out", "out"], "showers": [" "], "presidents": [" ", " ", " ", " "], "duffel": ["bag"], "smart": ["with"], "gave": ["her"], "real": ["i"], "around": ["i", "i", "i", "i"], "read": ["all"], "showing": ["they"], "gonna": ["lay"], "dark": [" "], "game": ["im"], "biz": [" "], "know": ["is", "what", "im", "that"], "using": ["the"], "unique": ["booty"], "knock": ["the"], "fleas": [" "], "like": ["talkin", "tarter", "sand", "this", "this", "i", "raking", "the", "em", "em", "i", "i", "im", "a", "geranimo", "an", "a"], "lost": [" "], "perpetual": ["its"], "accelerating": ["im"], "zans": [" "], "beverly": ["check"], "chick": ["that"], "clap": ["when"], "nigga": ["been", "wanted", "breathin", "im", "probably"], "deal": ["bet"], "doll": [" "], "fucking": ["with", "with", "with", "with"], "scared": ["of"], "back": ["ever", "go", "to"], "dead": ["presidents", "presidents", "presidents", "presidents"], "hair": ["nappy", "from", "shawty"], "engagin": ["where"], "holler": ["at"], "mirror": ["how", " ", "pretending"], "home": ["to"], "mustang": ["gt"], "indigent": ["cant"], "scale": [" "], "for": ["the", "the", "the", "the", "the", "the", "the", "the", "the", "the", "the", "the", "the", "the", "the", "the", "them", "the", "the", "the", "the", "the", "the", "the", "the", "me", "the", "the", "the", "the", "the", "the", "the", "the", "the", "undressin", "caressin", "you", "college", "you"], "memories": ["haunting"], "celibate": [" "], "comments": [" "], "everything": ["is", "on"], "911": [" "], "doin": ["numbers"], "hustle": ["you", "you", "you", "you"], "be": ["interrupting", "making", "accelerating", "doing", "who", "who", "who", "who", "really", "too", "really", "questioning", "really", "counting", "fucking", "digging"], "knew": ["she"], "eating": [" "], "business": ["put"], "hyaenas": [" "], "carats": ["they"], "nowhere": ["by"], "super": ["thiiiiick"], "by": ["a", "they", "marvin", "the"], "plug": ["and", "and", "and", "and", "and", "and", "and", "and"], "faith": ["even"], "ok": ["then"], "yelling": ["you"], "anything": [" ", " "], "oh": ["my"], "of": ["my", "your", "biz", "chips", "this", "the", "her", "my", "it", "those", "hyaenas", "smiling", "smiling", "this", "me", "four", "just", "smiling", "smiling", "zans", "cash", "that"], "moscato": ["was"], "pockets": ["on", "you"], "wanna": ["know"], "or": ["you", "you", "you", "you", "wrong", "you"], "allowing": ["no"], "david": ["and"], "dagger": [" "], "spreading": ["her"], "down": ["here", " "], "harness": [" "], "apologize": ["im", "im", "im"], "couldnt": ["afford"], "your": ["concern", "barbie", "heart", "soul", "circle", "pockets", "girl"], "goliath": ["a"], "crowd": ["no"], "her": ["bodyguard", "pin", "hips", "shit", "a", "special", "regular", "first", "to", "cheeks", " ", "messages", "phone", "cellular", " ", " ", "legs", " ", "hair", " ", " ", "if", "dance", " ", " ", "on", "knees", "girlfriend"], "sneeze": [" "], "vegetables": [" "], "there": ["they"], "long": ["hair"], "why": ["you"], "start": ["the", " ", " "], "low": ["mileage"], "stars": [" "], "was": ["thinkin", "trying", "all", "trying", "trying", "trying", "just", "a", "me", "evident", "catchin", "sweet", "a", "celibate"], "starve": [" ", " ", " ", " "], "head": ["spent", "spent", "spent", "spent", "trippy"], "bitches": ["and", "and", "and", "and", "and", "and", "and", "and", "in", "in", "in", "out"], "but": ["bitch", "she"], "catchin": ["a"], "line": ["bumpin\u2019", "bumpin\u2019", "bumpin\u2019", "bumpin\u2019", "bumpin\u2019", "bumpin\u2019", "bumpin\u2019", "bumpin\u2019", "they", "they", "they", "on"], "trying": ["to", "to", "to", "to", " ", "to", " ", "to", "to", " "], "with": ["shorty", "the", "the", "the", "the", "low", "us", "it", "her", "her", "deceptions", "my", "the", "the", "me", "find", "me", "me", "the", "the", "my", "my", "my", "a", "no", "your", "a"], "eat": ["or", "or", "or", "or"], "he": ["say", "said", "can", "gave", "talking", "flashed", "was"], "pull": ["up", "up", "up", "up"], "made": ["men", "em", "a"], "evident": [" "], "inside": ["my"], "up": ["new", "in", "what", "head", "head", "as", "head", "head", "my", "out", "feeling"], "us": ["him", " "], "catching": ["feelings"], "emotional": ["attachments", "attachments", "attachments", "attachments"], "cheeks": [" "], "trips": [" "], "strawder": [" "], "gone": ["learn"], "constant": ["repeat"], "sticks": ["of"], "pin": ["you"], "am": ["not", "in"], "vans": ["in"], "an": ["a", "elephant"], "fly": ["i", "i", "i", "i", "i", "i", "i", "i", "i", "i", "i"], "as": ["i", "i"], "replica": [" "], "right": ["foot", "and", "or", "here"], "at": ["her", "the", "her", "glover", "trav"], "et": ["cetera"], "girlfriend": [" "], "happen": [" "], "shit": [" ", " "], "again": ["one", "i"], "no": ["attempts", "small", "safety", "safety", "awards", "air", "spectacle", "detective", "man", "infiltration", "he", "nigga", "fleas"], "when": ["she", "it", "they", "yo", "im", "everyones", "every", "you", "everyones", "every", "she"], "til": ["death", "you"], "5": ["am"], "you": ["choose", "gone", "tryna", "know", "just", "not", "to", "in", "ever", "the", "follow", "cannot", "eat", "starve", "are", "eat", "starve", "are", "eat", "starve", "are", "eat", "starve", "are", "serious", "i", "steppin", "know", "dont", "need", "need", "til", "gon", "gonna", "let", " ", "can", "had", "had", "and", "they", "find", "looking", "had", "had", "and", "they", "find", "taking", "find", "never"], "really": ["get", "grindin", "diamonds", "trying", "really", " ", "really", " ", "ballin", "sorry", "really", " ", "out", "really", " ", "diamonds", "trying", "really", " ", "really", " ", "ballin", "sorry", "really", " ", "out", "really", " ", "really", "put", "thought", "diamonds", "trying", "really", " ", "really", " ", "ballin", "sorry", "really", " ", "out", "really", " "], "smell": ["like"], "talkin": [" ", "bout"], "reckless": ["dont"], "repeat": [" "], "lend": [" "], "tarter": ["imma"], "teeth": [" ", "when"], "problems": [" "], "meaning": ["one", "one", "one", "one", "one"], "important": [" "], "hollered": ["at"], "fresh": ["with"], "friends": [" "], "goin": ["out"], "ago": ["i"], "came": ["home"], "dog": ["he", "ass"], "impatient": [" "], "mimic": ["pretenders", "pretenders", "pretenders", "pretenders"], "aiko": ["chewing"], "lying": ["i", "i", "i"], "time": ["father", "artist", "you"], "serious": [" "], "hello": ["what"]}